CHANGELOG.rst
MANIFEST.in
README.rst
setup.cfg
setup.py
pscore/__init__.py
pscore.egg-info/PKG-INFO
pscore.egg-info/SOURCES.txt
pscore.egg-info/dependency_links.txt
pscore.egg-info/requires.txt
pscore.egg-info/top_level.txt
pscore/clients/__init__.py
pscore/clients/grid/__init__.py
pscore/clients/grid/grid_client.py
pscore/clients/saucelabs/__init__.py
pscore/clients/saucelabs/sauceclient.py
pscore/clients/saucelabs/saucelabs_client.py
pscore/clients/skygrid/__init__.py
pscore/clients/skygrid/api/__init__.py
pscore/clients/skygrid/api/skygridapiclient.py
pscore/clients/skygrid/dao/__init__.py
pscore/clients/skygrid/dao/data.py
pscore/clients/skygrid/metadata/__init__.py
pscore/clients/skygrid/metadata/skygridmetadataclient.py
pscore/config/__init__.py
pscore/config/test_configuration.py
pscore/core/Logger.py
pscore/core/__init__.py
pscore/core/event_listeners.py
pscore/core/factories.py
pscore/core/finalizers.py
pscore/core/wd_extensions.py
pscore/core/wd_testcase.py
pscore/core/drivers/__init__.py
pscore/core/drivers/driver_helper.py
pscore/core/drivers/skygrid_driver.py
pscore/core/support/__init__.py
pscore/core/support/ps_wait.py
pscore/core/support/test_context.py
pscore/core/visual/__init__.py
pscore/core/visual/applitools_wrapper.py
pscore/nose2/__init__.py
pscore/nose2/tags.py