Metadata-Version: 1.1
Name: pscore
Version: 0.4.5
Summary: Python-Selenium framework module
Home-page: https://pypi.python.org/pypi/pscore
Author: Andrew Fowler
Author-email: andrew.fowler@skyscanner.net
License: UNKNOWN
Download-URL: https://pypi.python.org/pypi/pscore
Keywords: selenium,webdriver,saucelabs,grid
Platform: UNKNOWN
Classifier: Intended Audience :: Developers
Classifier: Programming Language :: Python :: 3.5
Classifier: Programming Language :: Python :: 2.7
Classifier: Topic :: Software Development :: Testing
Classifier: Topic :: Software Development :: Quality Assurance
Requires: selenium
